bedrock_agentcore/__init__.py
bedrock_agentcore/py.typed
bedrock_agentcore/_utils/__init__.py
bedrock_agentcore/_utils/endpoints.py
bedrock_agentcore/evaluation/__init__.py
bedrock_agentcore/evaluation/integrations/__init__.py
bedrock_agentcore/evaluation/integrations/strands_agents_evals/README.md
bedrock_agentcore/evaluation/integrations/strands_agents_evals/__init__.py
bedrock_agentcore/evaluation/integrations/strands_agents_evals/evaluator.py
bedrock_agentcore/evaluation/integrations/strands_agents_evals/py.typed
bedrock_agentcore/evaluation/span_to_adot_serializer/__init__.py
bedrock_agentcore/evaluation/span_to_adot_serializer/adot_models.py
bedrock_agentcore/evaluation/span_to_adot_serializer/strands_converter.py
bedrock_agentcore/evaluation/utils/__init__.py
bedrock_agentcore/evaluation/utils/cloudwatch_span_helper.py
bedrock_agentcore/identity/__init__.py
bedrock_agentcore/identity/auth.py
bedrock_agentcore/memory/README.md
bedrock_agentcore/memory/__init__.py
bedrock_agentcore/memory/client.py
bedrock_agentcore/memory/constants.py
bedrock_agentcore/memory/controlplane.py
bedrock_agentcore/memory/metadata-workflow.ipynb
bedrock_agentcore/memory/session.py
bedrock_agentcore/memory/integrations/__init__.py
bedrock_agentcore/memory/integrations/strands/README.md
bedrock_agentcore/memory/integrations/strands/__init__.py
bedrock_agentcore/memory/integrations/strands/bedrock_converter.py
bedrock_agentcore/memory/integrations/strands/config.py
bedrock_agentcore/memory/integrations/strands/py.typed
bedrock_agentcore/memory/integrations/strands/session_manager.py
bedrock_agentcore/memory/models/DictWrapper.py
bedrock_agentcore/memory/models/__init__.py
bedrock_agentcore/memory/models/filters.py
bedrock_agentcore/runtime/__init__.py
bedrock_agentcore/runtime/agent_core_runtime_client.py
bedrock_agentcore/runtime/app.py
bedrock_agentcore/runtime/context.py
bedrock_agentcore/runtime/models.py
bedrock_agentcore/runtime/utils.py
bedrock_agentcore/services/__init__.py
bedrock_agentcore-1.1.2.dist-info/METADATA
bedrock_agentcore-1.1.2.dist-info/WHEEL
bedrock_agentcore-1.1.2.dist-info/entry_points.txt
bedrock_agentcore-1.1.2.dist-info/licenses/LICENSE.txt
bedrock_agentcore-1.1.2.dist-info/licenses/NOTICE.txt
bedrock_agentcore-1.1.2.dist-info/RECORD
