Metadata-Version: 2.4
Name: bedrock-agentcore
Version: 1.1.2
Summary: An SDK for using Bedrock AgentCore
Project-URL: Homepage, https://github.com/aws/bedrock-agentcore-sdk-python
Project-URL: Bug Tracker, https://github.com/aws/bedrock-agentcore-sdk-python/issues
Project-URL: Documentation, https://github.com/aws/bedrock-agentcore-sdk-python
Author-email: AWS <opensource@amazon.com>
License: Apache-2.0
License-File: LICENSE.txt
License-File: NOTICE.txt
Classifier: Development Status :: 3 - Alpha
Classifier: Intended Audience :: Developers
Classifier: License :: OSI Approved :: Apache Software License
Classifier: Operating System :: OS Independent
Classifier: Programming Language :: Python :: 3
Classifier: Programming Language :: Python :: 3.10
Classifier: Programming Language :: Python :: 3.11
Classifier: Programming Language :: Python :: 3.12
Classifier: Programming Language :: Python :: 3.13
Classifier: Topic :: Scientific/Engineering :: Artificial Intelligence
Classifier: Topic :: Software Development :: Libraries :: Python Modules
Requires-Python: >=3.10
Requires-Dist: boto3>=1.40.52
Requires-Dist: botocore>=1.40.52
Requires-Dist: pydantic<2.41.3,>=2.0.0
Requires-Dist: starlette>=0.46.2
Requires-Dist: typing-extensions<5.0.0,>=4.13.2
Requires-Dist: urllib3>=1.26.0
Requires-Dist: uvicorn>=0.34.2
Requires-Dist: websockets>=12.0
Provides-Extra: strands-agents
Requires-Dist: strands-agents>=1.1.0; extra == 'strands-agents'
Provides-Extra: strands-agents-evals
Requires-Dist: strands-agents-evals>=0.1.0; extra == 'strands-agents-evals'
